Metadata-Version: 1.0
Name: distPorb
Version: 0.2
Summary: Gaussian and binomial distributions
Home-page: UNKNOWN
Author: Ruba Dabbas
Author-email: uba@al-dabbas.com
License: UNKNOWN
Platform: UNKNOWN
